odoo/addons/pos_pricelist_technical/README.rst
odoo/addons/pos_pricelist_technical/__init__.py
odoo/addons/pos_pricelist_technical/__manifest__.py
odoo/addons/pos_pricelist_technical/i18n/fr.po
odoo/addons/pos_pricelist_technical/i18n/it.po
odoo/addons/pos_pricelist_technical/i18n/pos_pricelist_technical.pot
odoo/addons/pos_pricelist_technical/models/__init__.py
odoo/addons/pos_pricelist_technical/models/pos_order.py
odoo/addons/pos_pricelist_technical/models/pos_session.py
odoo/addons/pos_pricelist_technical/readme/CONFIGURE.rst
odoo/addons/pos_pricelist_technical/readme/CONTRIBUTORS.rst
odoo/addons/pos_pricelist_technical/readme/DESCRIPTION.rst
odoo/addons/pos_pricelist_technical/readme/USAGE.rst
odoo/addons/pos_pricelist_technical/static/description/icon.png
odoo/addons/pos_pricelist_technical/static/description/index.html
odoo/addons/pos_pricelist_technical/static/description/pos_config_form.png
odoo/addons/pos_pricelist_technical/static/description/pos_front_end_ui.png
odoo/addons/pos_pricelist_technical/static/src/js/SetPricelistButton.esm.js
odoo/addons/pos_pricelist_technical/static/src/xml/PartnerDetailsEdit.xml
odoo/addons/pos_pricelist_technical/views/templates.xml
odoo_addon_pos_pricelist_technical-16.0.1.0.0.2.dist-info/METADATA
odoo_addon_pos_pricelist_technical-16.0.1.0.0.2.dist-info/WHEEL
odoo_addon_pos_pricelist_technical-16.0.1.0.0.2.dist-info/top_level.txt
odoo_addon_pos_pricelist_technical-16.0.1.0.0.2.dist-info/RECORD
