Metadata-Version: 2.1
Name: odoo-addon-pos-pricelist-technical
Version: 16.0.1.0.0.2
Summary: Prevent technical pricelists from being displayed in the Point of Sale front-end UI
Home-page: https://github.com/OCA/pos
Author: GRAP,Odoo Community Association (OCA)
Author-email: support@odoo-community.org
License: AGPL-3
Platform: UNKNOWN
Classifier: Programming Language :: Python
Classifier: Framework :: Odoo
Classifier: Framework :: Odoo :: 16.0
Classifier: License :: OSI Approved :: GNU Affero General Public License v3
Requires-Python: >=3.10
Requires-Dist: odoo-addon-sale-pricelist-technical <16.1dev,>=16.0dev
Requires-Dist: odoo <16.1dev,>=16.0a
